bs_fura/__init__.py
bs_fura/__main__.py
bs_fura/access.py
bs_fura/access_async.py
bs_fura/audit.py
bs_fura/base_access.py
bs_fura/base_config.py
bs_fura/config.py
bs_fura/config_async.py
bs_fura/dao.py
bs_fura/dao_async.py
bs_fura/err_code.py
bs_fura/fura_davcache.py
bs_fura/fura_server.py
bs_fura/fura_server_impl.py
bs_fura/fura_server_impl_async.py
bs_fura/fura_token.py
bs_fura/jw_token.py
bs_fura/otp.py
bs_fura/otp_async.py
bs_fura/token_manager.py
bs_fura/token_sentry_pluggin.py
bs_fura/user_login.py
bs_fura/user_login_async.py
bs_fura/util.py
bs_fura/xfura.py
bs_fura/auth/__init__.py
bs_fura/auth/auth.py
bs_fura/auth/auth_async.py
bs_fura/auth/auth_password.py
bs_fura/auth/auth_password_async.py
bs_fura/auth/auth_token.py
bs_fura/auth/auth_token_async.py
bs_fura/auth/base_auth.py
bs_fura/auth/factory.py
bs_fura/braze/__init__.py
bs_fura/braze/auth_type_couplet.py
bs_fura/braze/bauth_policy.py
bs_fura/braze/brole_func_rel.py
bs_fura/braze/buser_login.py
bs_fura/braze/fura_async_server_interface.py
bs_fura/braze/fura_async_server_marshaler.py
bs_fura/braze/fura_client_interface.py
bs_fura/braze/fura_client_marshaler.py
bs_fura/braze/fura_client_server_impl.py
bs_fura/braze/fura_server_interface.py
bs_fura/braze/fura_server_marshaler.py
bs_fura/braze/reset_method_couplet.py
bs_fura/db/__init__.py
bs_fura/db/dao/postgresql/__init__.py
bs_fura/db/dao/postgresql/ada.py
bs_fura/db/dao/postgresql/ada_insert.py
bs_fura/db/dao/postgresql/ada_search.py
bs_fura/db/dao/postgresql/aga.py
bs_fura/db/dao/postgresql/aga_insert.py
bs_fura/db/dao/postgresql/aga_search.py
bs_fura/db/dao/postgresql/config.py
bs_fura/db/dao/postgresql/config_delete_one.py
bs_fura/db/dao/postgresql/config_insert.py
bs_fura/db/dao/postgresql/config_lock_one.py
bs_fura/db/dao/postgresql/config_search.py
bs_fura/db/dao/postgresql/config_select_all.py
bs_fura/db/dao/postgresql/config_select_one.py
bs_fura/db/dao/postgresql/config_update.py
bs_fura/db/dao/postgresql/eatok.py
bitsmiths_fura-2.2.3.dist-info/LICENCE
bitsmiths_fura-2.2.3.dist-info/METADATA
bitsmiths_fura-2.2.3.dist-info/WHEEL
bitsmiths_fura-2.2.3.dist-info/entry_points.txt
bitsmiths_fura-2.2.3.dist-info/top_level.txt
bitsmiths_fura-2.2.3.dist-info/RECORD
