Metadata-Version: 2.1
Name: bitsmiths-fura
Version: 2.2.3
Summary: The Bitsmiths Function-User-Role-Authenticator Package
Home-page: https://bitbucket.org/bitsmiths_za/bitsmiths
Author: Nicolas Milicevic, Steven van Niekerk, Darrly Daniels
Author-email: nicolas@bitsmiths.co.za, steven@bitsmiths.co.za, darryl@bitsmiths.co.za
License: MIT
Project-URL: Source, https://bitbucket.org/bitsmiths_za/bitsmiths
Keywords: libraries
Platform: unix
Platform: linux
Platform: osx
Platform: cygwin
Platform: win32
Classifier: Development Status :: 5 - Production/Stable
Classifier: Intended Audience :: Developers
Classifier: License :: OSI Approved :: MIT License
Classifier: Operating System :: MacOS :: MacOS X
Classifier: Operating System :: POSIX
Classifier: Programming Language :: Python :: 3
Classifier: Programming Language :: Python :: 3.7
Classifier: Programming Language :: Python :: 3.8
Classifier: Programming Language :: Python :: 3.9
Classifier: Programming Language :: Python :: 3 :: Only
Classifier: Topic :: Software Development :: Libraries
Classifier: Topic :: Software Development :: Libraries :: Python Modules
Requires-Python: >=3.10
License-File: LICENCE
Requires-Dist: bitsmiths-mettle (>=2.2.3)
Requires-Dist: bitsmiths-lib (>=2.1.4)
Requires-Dist: bitsmiths-audit (>=2.2.0)
Requires-Dist: bitsmiths-loco (>=2.2.0)
Requires-Dist: bcrypt
Requires-Dist: filetype
Requires-Dist: jwcrypto
Requires-Dist: sqlparse
Requires-Dist: pyyaml
